treecrypt.py
treecrypt-1.2.2.dist-info/licenses/LICENSE
treecrypt-1.2.2.dist-info/WHEEL
treecrypt-1.2.2.dist-info/METADATA
treecrypt-1.2.2.dist-info/RECORD
