Metadata-Version: 2.4
Name: TreeCrypt
Version: 1.2.2
Summary: A node-tree based encryption algorithm.
Keywords: encryption,node-trees,cryptography,cybersecurity
Author-email: MUmarShahbaz <m.umarshahbaz.2007@gmail.com>
Maintainer-email: MUmarShahbaz <m.umarshahbaz.2007@gmail.com>
Requires-Python: >=3.10
Classifier: Development Status :: 6 - Mature
Classifier: Intended Audience :: Developers
Classifier: License :: OSI Approved :: MIT License
Classifier: Programming Language :: Python
Classifier: Topic :: Security :: Cryptography
Classifier: Topic :: Software Development :: Libraries :: Python Modules
Classifier: Operating System :: OS Independent
License-File: LICENSE
Project-URL: Homepage, https://m-umar.me/projects/TreeCrypt
Project-URL: Source, https://github.com/MUmarShahbaz/TreeCrypt
Project-URL: Tracker, https://github.com/MUmarShahbaz/TreeCrypt/issues
